{
  "play": "10-content-moderation",
  "version": "1.0.0",
  "context": {
    "knowledge": [
      "T2-Responsible-AI",
      "F1-GenAI-Foundations"
    ],
    "waf": [
      "security",
      "responsible-ai",
      "reliability"
    ],
    "scope": "content-moderation-solution"
  },
  "primitives": {
    "agents": [
      "./.github/agents/builder.agent.md",
      "./.github/agents/reviewer.agent.md",
      "./.github/agents/tuner.agent.md"
    ],
    "instructions": [
      "./.github/instructions/azure-coding.instructions.md",
      "./.github/instructions/content-moderation-patterns.instructions.md",
      "./.github/instructions/security.instructions.md"
    ],
    "skills": [
      "./.github/skills/deploy-content-moderation/",
      "./.github/skills/evaluate-content-moderation/",
      "./.github/skills/tune-content-moderation/"
    ],
    "hooks": [
      "../../hooks/frootai-secrets-scanner/",
      "../../hooks/frootai-tool-guardian/",
      "../../hooks/frootai-governance-audit/"
    ],
    "guardrails": {
      "groundedness": 0.85,
      "coherence": 0.8,
      "relevance": 0.8,
      "safety": 0,
      "costPerQuery": 0.05
    }
  },
  "infrastructure": {
    "bicep": "./infra/main.bicep",
    "parameters": "./infra/parameters.json"
  },
  "toolkit": {
    "devkit": ".github/",
    "tunekit": "config/",
    "speckit": "spec/"
  }
}