{
  "name": "context-engineering",
  "description": "Context Engineering — maximize AI effectiveness with structured context, memory banks, knowledge wiring, and smart prompt assembly. Build context-aware agents that retrieve the right information at the right time.",
  "version": "1.0.0",
  "author": {
    "name": "FAI Contributors",
    "url": "https://frootai.dev"
  },
  "repository": "https://github.com/frootai/frootai",
  "license": "MIT",
  "keywords": [
    "context-engineering",
    "memory-bank",
    "knowledge-wiring",
    "rag",
    "context-assembly",
    "prompt-context"
  ],
  "agents": [
    "../../agents/fai-rag-expert.agent.md",
    "../../agents/fai-prompt-engineer.agent.md"
  ],
  "instructions": [
    "../../instructions/context-engineering-waf.instructions.md",
    "../../instructions/memory-bank-waf.instructions.md",
    "../../instructions/copilot-thought-logging-waf.instructions.md"
  ],
  "skills": [
    "../../skills/fai-what-context-needed/",
    "../../skills/fai-context-map/",
    "../../skills/fai-contextual-rag/",
    "../../skills/fai-remember/",
    "../../skills/fai-build-genai-rag/"
  ],
  "hooks": [
    "../../hooks/fai-secrets-scanner/",
    "../../hooks/fai-tool-guardian/",
    "../../hooks/fai-governance-audit/",
    "../../hooks/fai-session-logger/"
  ]
}
